Kekik/BIST.py
Kekik/Domain2IP.py
Kekik/Nesne.py
Kekik/__init__.py
Kekik/cache.py
Kekik/cli.py
Kekik/csv2dict.py
Kekik/dict2csv.py
Kekik/dict2json.py
Kekik/dosya2set.py
Kekik/dosya_indir.py
Kekik/hwid_kontrol.py
Kekik/link_islemleri.py
Kekik/list2html.py
Kekik/liste_fetis.py
Kekik/mail_gonder.py
Kekik/okunabilir_byte.py
Kekik/proxy_ver.py
Kekik/qr_ver.py
Kekik/ses_fetis.py
Kekik/slugify.py
Kekik/terminal_baslik.py
Kekik/txt_fetis.py
Kekik/unicode_tr.py
Kekik/zaman_donustur.py
Kekik/Sifreleme/AESManager.py
Kekik/Sifreleme/CryptoJS.py
Kekik/Sifreleme/HexCodec.py
Kekik/Sifreleme/NaysHash.py
Kekik/Sifreleme/Packer.py
Kekik/Sifreleme/StreamDecoder.py
Kekik/Sifreleme/StringCodec.py
Kekik/Sifreleme/__init__.py
Kekik/cache/__init__.py
Kekik/cache/backends.py
Kekik/cache/decorator.py
Kekik/cache/redis_pool.py
Kekik/cache/serializers.py
Kekik/kisi_ver/__init__.py
Kekik/kisi_ver/biyografiler.py
Kekik/kisi_ver/isimler.py
Kekik/kisi_ver/soyisimler.py
kekik-1.9.6.dist-info/licenses/LICENSE
kekik-1.9.6.dist-info/METADATA
kekik-1.9.6.dist-info/WHEEL
kekik-1.9.6.dist-info/entry_points.txt
kekik-1.9.6.dist-info/top_level.txt
kekik-1.9.6.dist-info/RECORD
