Metadata-Version: 2.4
Name: Kekik
Version: 1.9.6
Summary: İşlerimizi kolaylaştıracak fonksiyonların el altında durduğu kütüphane..
Home-page: https://github.com/keyiflerolsun/Kekik
Author: keyiflerolsun
Author-email: keyiflerolsun@gmail.com
License: GPLv3+
Keywords: Kekik,KekikAkademi,keyiflerolsun
Classifier: Development Status :: 5 - Production/Stable
Classifier: License :: OSI Approved :: GNU General Public License v3 or later (GPLv3+)
Classifier: Programming Language :: Python :: 3
Requires-Python: >=3.10
License-File: LICENSE
Requires-Dist: pip
Requires-Dist: setuptools
Requires-Dist: wheel
Requires-Dist: pytz
Requires-Dist: requests
Requires-Dist: aiohttp
Requires-Dist: httpx
Requires-Dist: parsel
Requires-Dist: cssselect
Requires-Dist: simplejson
Requires-Dist: rich
Requires-Dist: tabulate
Requires-Dist: pycryptodome
Requires-Dist: redis
Dynamic: author
Dynamic: author-email
Dynamic: classifier
Dynamic: description
Dynamic: description-content-type
Dynamic: home-page
Dynamic: keywords
Dynamic: license
Dynamic: license-file
Dynamic: requires-dist
Dynamic: requires-python
Dynamic: summary
